sirji_tools/__init__.py
sirji_tools/crawler/__init__.py
sirji_tools/crawler/base.py
sirji_tools/crawler/crawler.py
sirji_tools/crawler/factory.py
sirji_tools/crawler/github_handler.py
sirji_tools/crawler/pdf_handler.py
sirji_tools/crawler/web_page_handler.py
sirji_tools/logger/__init__.py
sirji_tools/logger/logger.py
sirji_tools/search/__init__.py
sirji_tools/search/search.py
sirji_tools-0.0.16.dist-info/LICENSE
sirji_tools-0.0.16.dist-info/METADATA
sirji_tools-0.0.16.dist-info/WHEEL
sirji_tools-0.0.16.dist-info/top_level.txt
sirji_tools-0.0.16.dist-info/RECORD
