Metadata-Version: 2.1
Name: sirji-tools
Version: 0.0.16
Summary: Crawler and search tools used by Sirji.
Home-page: https://github.com/sirji-ai/sirji
Author: Sirji
License: MIT
Requires-Python: >=3.6
License-File: LICENSE
Requires-Dist: requests ==2.31.0
Requires-Dist: pypdf2 ==3.0.1
Requires-Dist: markdownify ==0.11.6
Requires-Dist: playwright ==1.42.0
